pydbfill/__init__.py
pydbfill/pydbfill.py
pydbfill-0.1.6.dist-info/WHEEL
pydbfill-0.1.6.dist-info/METADATA
pydbfill-0.1.6.dist-info/RECORD
